Workbook
Name CurrentPrice: 'Cover'!B4
Name PriceTarget: 'Cover'!B5
Name Rating: 'Cover'!B3
Name WACC: 'WACC'!B7
Name TerminalGrowth: 'Assumptions'!B14
Name ExitMultiple: 'Assumptions'!B15
Name EV_Gordon: 'DCF'!B14
Name EV_Exit: 'DCF'!B15
Name EquityValue_Gordon: 'DCF'!B19
Name EquityValue_Exit: 'DCF'!B20
Name ImpliedPrice_Gordon: 'DCF'!B21
Name ImpliedPrice_Exit: 'DCF'!B22
Name NetDebt: 'DCF'!B17
Name SharesDiluted: 'DCF'!B18
Name Comps_ImpliedPrice_EBITDA: 'Trading Comps'!B14
Name LBO_IRR: 'LBO'!B18
Name LBO_MOIC: 'LBO'!B19
Name RevenueCAGR: 'Model IS'!B16

Sheet Cover
A1: DECKERS OUTDOOR CORP (DECK) — Initiating Coverage
A3: Rating | B3: Buy
A4: Current price | B4: 99.68
A5: 12-mo price target | B5: 128
A6: Implied upside | B6: =B5/B4-1
A8: Valuation triangulation
A9: DCF (Gordon) | B9: ='DCF'!B21
A10: DCF (exit) | B10: ='DCF'!B22
A11: Comps (EV/EBITDA) | B11: ='Trading Comps'!B14
A13: Educational project — not investment advice. SEC EDGAR data used per fair-access policy; no SEC endorsement implied.

Sheet Assumptions
A1: Assumptions (inputs — blue)
A3: Projection year | B3: Y1 | C3: Y2 | D3: Y3 | E3: Y4 | F3: Y5
A4: Revenue growth | B4: 0.09 | C4: 0.08 | D4: 0.07 | E4: 0.06 | F4: 0.05
A5: Gross margin | B5: 0.575 | C5: 0.575 | D5: 0.57 | E5: 0.57 | F5: 0.565
A6: SG&A % revenue | B6: 0.345 | C6: 0.345 | D6: 0.345 | E6: 0.345 | F6: 0.345
A7: R&D % revenue | B7: 0 | C7: 0 | D7: 0 | E7: 0 | F7: 0
A8: Capex % revenue | B8: 0.016 | C8: 0.016 | D8: 0.016 | E8: 0.016 | F8: 0.016
A9: D&A % revenue | B9: 0.018 | C9: 0.018 | D9: 0.018 | E9: 0.018 | F9: 0.018
A10: Tax rate | B10: 0.235 | C10: 0.235 | D10: 0.235 | E10: 0.235 | F10: 0.235
A11: Change in working capital | B11: -6.8365568e+08 | C11: -88409814 | D11: -89684811 | E11: -76993038 | F11: -74841596
A13: Min cash (revolver floor) | B13: 400000000
A14: Terminal growth (g) | B14: 0.03
A15: Exit EV/EBITDA | B15: 11
A17: WACC / CAPM inputs
A18: Risk-free rate | B18: 0.043
A19: Beta | B19: 1.05
A20: Equity risk premium | B20: 0.05
A21: Pre-tax cost of debt | B21: 0.06
A22: WACC tax rate | B22: 0.235
A23: Market cap | B23: 13576416000
A24: Total debt | B24: 0

Sheet Historical IS
A1: Historical IS (reported — ties to XBRL)
B3: FY2008 | C3: FY2009 | D3: FY2010 | E3: FY2011 | F3: FY2012 | G3: FY2013 | H3: FY2015 | I3: FY2016 | J3: FY2017 | K3: FY2018 | L3: FY2019 | M3: FY2020 | N3: FY2021 | O3: FY2022 | P3: FY2023 | Q3: FY2024 | R3: FY2025 | S3: FY2026
A4: revenue | B4: 689445000 | C4: 813177000 | D4: 1000989000 | E4: 1377283000 | F4: 1414398000 | G4: 1556618000 | H4: 1817057000 | I4: 1875197000 | J4: 1790147000 | K4: 1903339000 | L4: 2020437000 | M4: 2132689000 | N4: 2545641000 | O4: 3150339000 | P4: 3627286000 | Q4: 4287763000 | R4: 4985612000 | S4: 5472296000
A5: cost_of_revenue | B5: 384127000 | C5: 442087000 | D5: 498051000 | E5: 698288000 | F5: 782244000 | G5: 820135000 | H5: 938949000 | I5: 1028529000 | J5: 954912000 | K5: 971697000 | L5: 980187000 | M5: 1029016000 | N5: 1171551000 | O5: 1542788000 | P5: 1801916000 | Q5: 1902275000 | R5: 2099949000 | S5: 2314570000
A6: gross_profit | B6: 305318000 | C6: 371090000 | D6: 502938000 | E6: 678995000 | F6: 632154000 | G6: 736483000 | H6: 878108000 | I6: 846668000 | J6: 835235000 | K6: 931642000 | L6: 1040250000 | M6: 1103673000 | N6: 1374090000 | O6: 1607551000 | P6: 1825370000 | Q6: 2385488000 | R6: 2885663000 | S6: 3157726000
A7: operating_income | B7: 116919000 | C7: 181247000 | D7: 249088000 | E7: 284838000 | F7: 186948000 | G7: 207897000 | H7: 224419000 | I7: 162127000 | J7: -1919000 | K7: 222584000 | L7: 327320000 | M7: 338135000 | N7: 504205000 | O7: 564707000 | P7: 652751000 | Q7: 927514000 | R7: 1179092000 | S7: 1262903000
A8: net_income | B8: 73948000 | C8: 116786000 | D8: 158235000 | E8: 201858000 | F8: 129014000 | G8: 145689000 | H8: 161780000 | I8: 122265000 | J8: 5710000 | K8: 114394000 | L8: 264308000 | M8: 276142000 | N8: 382575000 | O8: 451949000 | P8: 516822000 | Q8: 759563000 | R8: 966091000 | S8: 1024071000

Sheet Historical BS
A1: Historical BS (reported — ties to XBRL)
B3: FY2008 | C3: FY2009 | D3: FY2010 | E3: FY2011 | F3: FY2012 | G3: FY2013 | H3: FY2015 | I3: FY2016 | J3: FY2017 | K3: FY2018 | L3: FY2019 | M3: FY2020 | N3: FY2021 | O3: FY2022 | P3: FY2023 | Q3: FY2024 | R3: FY2025 | S3: FY2026
A4: cash_and_equivalents | B4: 176804000 | C4: 315862000 | D4: 445226000 | E4: 263606000 | F4: 110247000 | G4: 237125000 | H4: 225143000 | I4: 245956000 | J4: 291764000 | K4: 429970000 | L4: 589692000 | M4: 649436000 | N4: 1089361000 | O4: 843527000 | P4: 981795000 | Q4: 1502051000 | R4: 1889188000 | S4: 1907249000
A5: total_assets | C5: 599043000 | D5: 808994000 | E5: 1146196000 | F5: 1068064000 | G5: 1259729000 | H5: 1169933000 | I5: 1278068000 | J5: 1191780000 | K5: 1264379000 | L5: 1427206000 | M5: 1765118000 | N5: 2167705000 | O5: 2332250000 | P5: 2556203000 | Q5: 3135579000 | R5: 3570252000 | S5: 3687765000
A6: total_stockholders_equity | B6: 384665000 | C6: 491358000 | D6: 652987000 | E6: 835936000 | F6: 738801000 | G6: 888119000 | H6: 937012000 | I6: 967471000 | J6: 954255000 | K6: 940779000 | L6: 1045130000 | M6: 1140120000 | N6: 1444225000 | O6: 1538825000 | P6: 1765733000 | Q6: 2107468000 | R6: 2513013000 | S6: 2499638000

Sheet Historical CF
A1: Historical CF (reported — ties to XBRL)
B3: FY2008 | C3: FY2009 | D3: FY2010 | E3: FY2011 | F3: FY2012 | G3: FY2013 | H3: FY2015 | I3: FY2016 | J3: FY2017 | K3: FY2018 | L3: FY2019 | M3: FY2020 | N3: FY2021 | O3: FY2022 | P3: FY2023 | Q3: FY2024 | R3: FY2025 | S3: FY2026
A4: cash_from_operations | B4: 53276000 | C4: 185474000 | D4: 139922000 | E4: 30091000 | F4: 163906000 | G4: 262125000 | H4: 169654000 | I4: 125813000 | J4: 199330000 | K4: 327355000 | L4: 359505000 | M4: 286334000 | N4: 596217000 | O4: 172353000 | P4: 537422000 | Q4: 1033184000 | R4: 1044523000 | S4: 1181955000
A5: capital_expenditures | B5: 22218000 | C5: 13699000 | D5: 22489000 | E5: 55538000 | F5: 61575000 | G5: 79829000 | H5: 91147000 | I5: 66186000 | J5: 44499000 | K5: 34813000 | L5: 29086000 | M5: 32455000 | N5: 32218000 | O5: 51017000 | P5: 81025000 | Q5: 89365000 | R5: 86171000 | S5: 84623000

Sheet Model IS
A1: Model Income Statement (projection)
A3: Line ($) | B3: Base | C3: Y1 | D3: Y2 | E3: Y3 | F3: Y4 | G3: Y5
A4: Revenue | B4: 5472296000 | C4: =B4*(1+'Assumptions'!B4) | D4: =C4*(1+'Assumptions'!C4) | E4: =D4*(1+'Assumptions'!D4) | F4: =E4*(1+'Assumptions'!E4) | G4: =F4*(1+'Assumptions'!F4)
A5: Gross profit | C5: =C4*'Assumptions'!B5 | D5: =D4*'Assumptions'!C5 | E5: =E4*'Assumptions'!D5 | F5: =F4*'Assumptions'!E5 | G5: =G4*'Assumptions'!F5
A6: SG&A | C6: =C4*'Assumptions'!B6 | D6: =D4*'Assumptions'!C6 | E6: =E4*'Assumptions'!D6 | F6: =F4*'Assumptions'!E6 | G6: =G4*'Assumptions'!F6
A7: R&D | C7: =C4*'Assumptions'!B7 | D7: =D4*'Assumptions'!C7 | E7: =E4*'Assumptions'!D7 | F7: =F4*'Assumptions'!E7 | G7: =G4*'Assumptions'!F7
A8: EBIT | C8: =C5-C6-C7 | D8: =D5-D6-D7 | E8: =E5-E6-E7 | F8: =F5-F6-F7 | G8: =G5-G6-G7
A9: D&A | C9: =C4*'Assumptions'!B9 | D9: =D4*'Assumptions'!C9 | E9: =E4*'Assumptions'!D9 | F9: =F4*'Assumptions'!E9 | G9: =G4*'Assumptions'!F9
A10: EBITDA | C10: =C8+C9 | D10: =D8+D9 | E10: =E8+E9 | F10: =F8+F9 | G10: =G8+G9
A11: Net interest income | C11: 85148349 | D11: 1.1695498e+08 | E11: 1.6463303e+08 | F11: 2.1658157e+08 | G11: 2.7260455e+08
A12: Pre-tax income | C12: =C8+C11 | D12: =D8+D11 | E12: =E8+E11 | F12: =F8+F11 | G12: =G8+G11
A13: Taxes | C13: =C12*'Assumptions'!B10 | D13: =D12*'Assumptions'!C10 | E13: =E12*'Assumptions'!D10 | F13: =F12*'Assumptions'!E10 | G13: =G12*'Assumptions'!F10
A14: Net income | C14: =C12-C13 | D14: =D12-D13 | E14: =E12-E13 | F14: =F12-F13 | G14: =G12-G13
A16: Revenue CAGR (proj) | B16: =(G4/B4)^(1/5)-1

Sheet Model BS
A1: Model Balance Sheet
A3: Line ($) | B3: FY2027E | C3: FY2028E | D3: FY2029E | E3: FY2030E | F3: FY2031E
A4: Cash & equivalents | B4: 2.3501684e+09 | C4: 3.4975807e+09 | D4: 4.7340709e+09 | E4: 6.0950074e+09 | F4: 7.5352203e+09
A5: Accounts receivable | B5: 6.53677e+08 | C5: 7.0597116e+08 | D5: 7.5538914e+08 | E5: 8.0071249e+08 | F5: 8.4074812e+08
A6: Inventory | B6: 7.63985e+08 | C6: 8.251038e+08 | D6: 8.9324766e+08 | E6: 9.4684252e+08 | F6: 1.0057449e+09
A7: Total current assets | B7: 3.8499444e+09 | C7: 5.1107697e+09 | D7: 6.4648217e+09 | E7: 7.9246764e+09 | F7: 9.4638274e+09
A8: Property, plant & equipment, net | B8: 3.2585239e+08 | C8: 3.1296842e+08 | D8: 2.9918257e+08 | E8: 2.8456957e+08 | F8: 2.6922591e+08
A9: Goodwill & intangibles | B9: 13990000 | C9: 13990000 | D9: 13990000 | E9: 13990000 | F9: 13990000
A10: Total assets | B10: 4.6068588e+09 | C10: 5.8548001e+09 | D10: 7.1950663e+09 | E10: 8.6403079e+09 | F10: 1.0164115e+10
A11: Accounts payable | B11: 3.1253932e+08 | C11: 3.3754246e+08 | D11: 3.654195e+08 | E11: 3.8734467e+08 | F11: 4.1144111e+08
A12: Total current liabilities | B12: 5.6764332e+08 | C12: 5.9264646e+08 | D12: 6.205235e+08 | E12: 6.4244867e+08 | F12: 6.6654511e+08
A13: Total liabilities | B13: 9.9397532e+08 | C13: 1.0189785e+09 | D13: 1.0468555e+09 | E13: 1.0687807e+09 | F13: 1.0928771e+09
A14: Retained earnings | B14: 3.3610075e+09 | C14: 4.5839457e+09 | D14: 5.8963348e+09 | E14: 7.3196513e+09 | F14: 8.8193622e+09
A15: Total stockholders' equity | B15: 3.6128835e+09 | C15: 4.8358217e+09 | D15: 6.1482108e+09 | E15: 7.5715273e+09 | F15: 9.0712382e+09
A17: Engine-computed & invariant-checked: BS balances every period; CFS ending cash ties to BS cash; RE and PP&E rolls hold.

Sheet Model CF
A1: Model Cash Flow Statement
A3: Line ($) | B3: FY2027E | C3: FY2028E | D3: FY2029E | E3: FY2030E | F3: FY2031E
A4: Net income | B4: 1.1146455e+09 | C4: 1.2229381e+09 | D4: 1.3123891e+09 | E4: 1.4233165e+09 | F4: 1.4997109e+09
A5: Depreciation & amortization | B5: 1.0736645e+08 | C5: 1.1595576e+08 | D5: 1.2407267e+08 | E5: 1.3151703e+08 | F5: 1.3809288e+08
A6: Change in working capital | B6: -6.8365568e+08 | C6: -88409814 | D6: -89684811 | E6: -76993038 | F6: -74841596
A7: Cash from operations | B7: 5.3835628e+08 | C7: 1.2504841e+09 | D7: 1.346777e+09 | E7: 1.4778405e+09 | F7: 1.5629622e+09
A8: Capital expenditures | B8: -95436842 | C8: -1.0307179e+08 | D8: -1.1028681e+08 | E8: -1.1690402e+08 | F8: -1.2274922e+08
A9: Cash from investing | B9: -95436842 | C9: -1.0307179e+08 | D9: -1.1028681e+08 | E9: -1.1690402e+08 | F9: -1.2274922e+08
A10: Net change in cash | B10: 4.4291944e+08 | C10: 1.1474123e+09 | D10: 1.2364902e+09 | E10: 1.3609364e+09 | F10: 1.440213e+09
A12: Engine-computed & invariant-checked: BS balances every period; CFS ending cash ties to BS cash; RE and PP&E rolls hold.

Sheet WACC
A1: WACC (CAPM)
A3: Cost of equity (Ke) | B3: ='Assumptions'!B18+'Assumptions'!B19*'Assumptions'!B20
A4: After-tax cost of debt | B4: ='Assumptions'!B21*(1-'Assumptions'!B22)
A5: Equity weight | B5: ='Assumptions'!B23/('Assumptions'!B23+'Assumptions'!B24)
A6: Debt weight | B6: ='Assumptions'!B24/('Assumptions'!B23+'Assumptions'!B24)
A7: WACC | B7: =B5*B3+B6*B4

Sheet DCF
A1: Discounted Cash Flow (FCFF)
A3: Projection year | B3: Y1 | C3: Y2 | D3: Y3 | E3: Y4 | F3: Y5
A4: FCFF | B4: ='Model IS'!C8*(1-'Assumptions'!B10)+'Model IS'!C9-'Model IS'!C4*'Assumptions'!B8+B7 | C4: ='Model IS'!D8*(1-'Assumptions'!C10)+'Model IS'!D9-'Model IS'!D4*'Assumptions'!C8+C7 | D4: ='Model IS'!E8*(1-'Assumptions'!D10)+'Model IS'!E9-'Model IS'!E4*'Assumptions'!D8+D7 | E4: ='Model IS'!F8*(1-'Assumptions'!E10)+'Model IS'!F9-'Model IS'!F4*'Assumptions'!E8+E7 | F4: ='Model IS'!G8*(1-'Assumptions'!F10)+'Model IS'!G9-'Model IS'!G4*'Assumptions'!F8+F7
A5: Discount factor | B5: =1/(1+'WACC'!B7)^(1-0.5) | C5: =1/(1+'WACC'!B7)^(2-0.5) | D5: =1/(1+'WACC'!B7)^(3-0.5) | E5: =1/(1+'WACC'!B7)^(4-0.5) | F5: =1/(1+'WACC'!B7)^(5-0.5)
A6: PV of FCFF | B6: =B4*B5 | C6: =C4*C5 | D6: =D4*D5 | E6: =E4*E5 | F6: =F4*F5
A7: Change in working capital | B7: ='Assumptions'!B11 | C7: ='Assumptions'!C11 | D7: ='Assumptions'!D11 | E7: ='Assumptions'!E11 | F7: ='Assumptions'!F11
A8: PV explicit FCFF | B8: =SUM(B6:F6)
A9: Terminal value (Gordon) | B9: =B24*(1+'Assumptions'!B14)/('WACC'!B7-'Assumptions'!B14)
A10: Terminal value (exit) | B10: ='Model IS'!G10*'Assumptions'!B15
A11: PV terminal (Gordon) | B11: =B9*F5
A12: PV terminal (exit) | B12: =B10*B25
A14: EV (Gordon) | B14: =B8+B11
A15: EV (exit) | B15: =B8+B12
A17: Net debt | B17: -1907249000
A18: Shares diluted | B18: 136200000
A19: Equity value (Gordon) | B19: =B14-B17
A20: Equity value (exit) | B20: =B15-B17
A21: Implied price (Gordon) | B21: =B19/B18
A22: Implied price (exit) | B22: =B20/B18
A24: Terminal FCFF (normalized) | B24: 9.8252258e+08
A25: Exit discount factor (full-year) | B25: =1/(1+'WACC'!B7)^5

Sheet Trading Comps
A1: Trading Comps
A3: Ticker | B3: EV | C3: EV/Revenue | D3: EV/EBITDA | E3: P/E
A4: NKE | B4: 106939000000 | C4: 2.3048192 | E4: 34.285714
A5: CROX | B5: 5415000000 | C5: 1.3401319 | D5: 23.667268
A6: WWW | B6: 1440000000 | C6: 0.76828683 | D6: 8.1771721 | E6: 15.031315
A7: SHOO | B7: 2130000000 | C7: 0.84472925 | D7: 18.650182 | E7: 43.453425
A8: COLM | B8: 3472000000 | C8: 1.0219727 | D8: 13.157795 | E8: 19.591026
A9: VFC | B9: 5460000000 | C9: 0.56844168 | D9: 6.3703334 | E9: 21.418484
A10: BOOT | B10: 4950000000 | C10: 2.1962332 | D10: 13.102205 | E10: 21.914291
A11: CAL | B11: 680000000 | C11: 0.24656862 | D11: 12.439859
A13: Median EV/EBITDA | D13: =MEDIAN(D4:D11)
A14: Implied price (EV/EBITDA) | B14: 128.77832

Sheet Precedents
A1: Precedent Transactions
A3: Date | B3: Acquirer | C3: Target | D3: EV | E3: EV/Rev | F3: EV/EBITDA | G3: Source
A4: 2025-05-05 | B4: 3G Capital | C4: Skechers U.S.A. Inc. | D4: 9400000000 | G4: Skechers press release, 2025-05-05: 3G Capital to acquire Skechers for $63.00/share, ~$9.4B enterprise value
A5: 2021-08-12 | B5: Authentic Brands Group | C5: Reebok (from adidas AG) | D5: 2500000000 | G5: adidas AG press release, 2021-08-12: divestiture of Reebok to ABG for up to EUR 2.1B (~$2.5B)
A6: 2020-11-09 | B6: VF Corporation | C6: Supreme | D6: 2100000000 | G6: VF Corporation press release, 2020-11-09: acquisition of Supreme for $2.1B
A7: 2012-05-01 | B7: Wolverine World Wide (with Blum Capital & Golden Gate Capital) | C7: Collective Brands Performance + Lifestyle Group (Sperry / Saucony / Keds / Stride Rite) | D7: 1230000000 | G7: Wolverine World Wide press release, 2012-05-01: acquisition of Collective Brands' PLG for ~$1.23B
A8: 2011-06-13 | B8: VF Corporation | C8: The Timberland Company | D8: 2300000000 | G8: VF Corporation press release, 2011-06-13: acquisition of Timberland for $43.00/share, ~$2.3B
A9: 2024-12-17 | B9: Steven Madden Ltd. | C9: Kurt Geiger (from Cinven) | D9: 360000000 | G9: Steve Madden press release, 2024-12-17: agreement to acquire Kurt Geiger for ~GBP 289M (~$360M)

Sheet LBO
A1: LBO
A3: Sources & Uses
A4: Source: new_debt | B4: 8130027000
A5: Source: sponsor_equity | B5: 8130027000
A6: Use: purchase_enterprise_value | B6: 16260054000
A7: Use: transaction_fees | B7: 0
A9: Debt schedule (levered cash sweep)
A10: Year | B10: Begin debt | C10: Cash interest | D10: Levered FCF | E10: Sweep | F10: End debt | G10: Cash balance
A11: Y1 | B11: 8130027000 | C11: 569101890 | D11: 4.9233474e+08 | E11: 3.6925105e+08 | F11: 7.7607759e+09 | G11: 1.2308368e+08
A12: Y2 | B12: 7.7607759e+09 | C12: 5.4325432e+08 | D12: 6.0309724e+08 | E12: 4.5232293e+08 | F12: 7.308453e+09 | G12: 2.73858e+08
A13: Y3 | B13: 7.308453e+09 | C13: 5.1159171e+08 | D13: 6.8863902e+08 | E13: 5.1647926e+08 | F13: 6.7919737e+09 | G13: 4.4601775e+08
A14: Y4 | B14: 6.7919737e+09 | C14: 4.7543816e+08 | D14: 7.9680641e+08 | E14: 5.9760481e+08 | F14: 6.1943689e+09 | G14: 6.4521935e+08
A15: Y5 | B15: 6.1943689e+09 | C15: 4.3360583e+08 | D15: 8.7290624e+08 | E15: 6.5467968e+08 | F15: 5.5396893e+09 | G15: 8.6344591e+08
A17: Exit equity value | B17: 1.5408599e+10
A18: IRR | B18: 0.13640786
A19: MOIC | B19: 1.8952703
A20: Illustrative only — DECK is net-cash today; this shows what leverage could do.

Sheet Sensitivities
A1: Sensitivities: implied price = f(WACC, g)
A3: g \ WACC | B3: ='WACC'!B7+-0.01 | C3: ='WACC'!B7+-0.005 | D3: ='WACC'!B7+0.0 | E3: ='WACC'!B7+0.005 | F3: ='WACC'!B7+0.01
A4: ='Assumptions'!B14+-0.01 | B4: =(('DCF'!B8+'DCF'!B24*(1+A4)/(B3-A4)/(1+B3)^(5-0.5))-'DCF'!B17)/'DCF'!B18 | C4: =(('DCF'!B8+'DCF'!B24*(1+A4)/(C3-A4)/(1+C3)^(5-0.5))-'DCF'!B17)/'DCF'!B18 | D4: =(('DCF'!B8+'DCF'!B24*(1+A4)/(D3-A4)/(1+D3)^(5-0.5))-'DCF'!B17)/'DCF'!B18 | E4: =(('DCF'!B8+'DCF'!B24*(1+A4)/(E3-A4)/(1+E3)^(5-0.5))-'DCF'!B17)/'DCF'!B18 | F4: =(('DCF'!B8+'DCF'!B24*(1+A4)/(F3-A4)/(1+F3)^(5-0.5))-'DCF'!B17)/'DCF'!B18
A5: ='Assumptions'!B14+-0.005 | B5: =(('DCF'!B8+'DCF'!B24*(1+A5)/(B3-A5)/(1+B3)^(5-0.5))-'DCF'!B17)/'DCF'!B18 | C5: =(('DCF'!B8+'DCF'!B24*(1+A5)/(C3-A5)/(1+C3)^(5-0.5))-'DCF'!B17)/'DCF'!B18 | D5: =(('DCF'!B8+'DCF'!B24*(1+A5)/(D3-A5)/(1+D3)^(5-0.5))-'DCF'!B17)/'DCF'!B18 | E5: =(('DCF'!B8+'DCF'!B24*(1+A5)/(E3-A5)/(1+E3)^(5-0.5))-'DCF'!B17)/'DCF'!B18 | F5: =(('DCF'!B8+'DCF'!B24*(1+A5)/(F3-A5)/(1+F3)^(5-0.5))-'DCF'!B17)/'DCF'!B18
A6: ='Assumptions'!B14+0.0 | B6: =(('DCF'!B8+'DCF'!B24*(1+A6)/(B3-A6)/(1+B3)^(5-0.5))-'DCF'!B17)/'DCF'!B18 | C6: =(('DCF'!B8+'DCF'!B24*(1+A6)/(C3-A6)/(1+C3)^(5-0.5))-'DCF'!B17)/'DCF'!B18 | D6: =(('DCF'!B8+'DCF'!B24*(1+A6)/(D3-A6)/(1+D3)^(5-0.5))-'DCF'!B17)/'DCF'!B18 | E6: =(('DCF'!B8+'DCF'!B24*(1+A6)/(E3-A6)/(1+E3)^(5-0.5))-'DCF'!B17)/'DCF'!B18 | F6: =(('DCF'!B8+'DCF'!B24*(1+A6)/(F3-A6)/(1+F3)^(5-0.5))-'DCF'!B17)/'DCF'!B18
A7: ='Assumptions'!B14+0.005 | B7: =(('DCF'!B8+'DCF'!B24*(1+A7)/(B3-A7)/(1+B3)^(5-0.5))-'DCF'!B17)/'DCF'!B18 | C7: =(('DCF'!B8+'DCF'!B24*(1+A7)/(C3-A7)/(1+C3)^(5-0.5))-'DCF'!B17)/'DCF'!B18 | D7: =(('DCF'!B8+'DCF'!B24*(1+A7)/(D3-A7)/(1+D3)^(5-0.5))-'DCF'!B17)/'DCF'!B18 | E7: =(('DCF'!B8+'DCF'!B24*(1+A7)/(E3-A7)/(1+E3)^(5-0.5))-'DCF'!B17)/'DCF'!B18 | F7: =(('DCF'!B8+'DCF'!B24*(1+A7)/(F3-A7)/(1+F3)^(5-0.5))-'DCF'!B17)/'DCF'!B18
A8: ='Assumptions'!B14+0.01 | B8: =(('DCF'!B8+'DCF'!B24*(1+A8)/(B3-A8)/(1+B3)^(5-0.5))-'DCF'!B17)/'DCF'!B18 | C8: =(('DCF'!B8+'DCF'!B24*(1+A8)/(C3-A8)/(1+C3)^(5-0.5))-'DCF'!B17)/'DCF'!B18 | D8: =(('DCF'!B8+'DCF'!B24*(1+A8)/(D3-A8)/(1+D3)^(5-0.5))-'DCF'!B17)/'DCF'!B18 | E8: =(('DCF'!B8+'DCF'!B24*(1+A8)/(E3-A8)/(1+E3)^(5-0.5))-'DCF'!B17)/'DCF'!B18 | F8: =(('DCF'!B8+'DCF'!B24*(1+A8)/(F3-A8)/(1+F3)^(5-0.5))-'DCF'!B17)/'DCF'!B18

Sheet Football Field
A1: Football Field (valuation ranges)
A3: Method | B3: Low | C3: High
A4: DCF (Gordon–Exit) | B4: ='DCF'!B21 | C4: ='DCF'!B22
A5: Comps (EV/EBITDA) | B5: ='Trading Comps'!B14 | C5: ='Trading Comps'!B14
A7: Current price | B7: ='Cover'!B4
A8: Price target | B8: ='Cover'!B5
